dnssplitter/DNSSplitter.py
dnssplitter/__init__.py
dnssplitter/domains.py
dnssplitter/scripts/__init__.py
dnssplitter/scripts/dbdnssplit.py
dnssplitter/scripts/dnssplit.py
dnssplitter/tests/test_fsdb_splitter.py
dnssplitter/tests/test_psl_parser.py
dnssplitter-1.1.1.dist-info/METADATA
dnssplitter-1.1.1.dist-info/WHEEL
dnssplitter-1.1.1.dist-info/entry_points.txt
dnssplitter-1.1.1.dist-info/RECORD
