Metadata-Version: 2.3
Name: dnssplitter
Version: 1.1.1
Summary: A fast python implementation of breaking down DNS domains into parts.
Project-URL: Homepage, https://github.com/hardaker/dnssplitter
Author-email: Wes Hardaker <opensource@hardakers.net>
Classifier: Operating System :: OS Independent
Classifier: Programming Language :: Python :: 3
Requires-Python: >=3
